pip_spaced/__init__.py
pip_spaced/cli.py
pip_spaced/pip_spaced.py
pip_spaced-0.1.0.dist-info/AUTHORS.rst
pip_spaced-0.1.0.dist-info/LICENSE
pip_spaced-0.1.0.dist-info/METADATA
pip_spaced-0.1.0.dist-info/WHEEL
pip_spaced-0.1.0.dist-info/entry_points.txt
pip_spaced-0.1.0.dist-info/top_level.txt
pip_spaced-0.1.0.dist-info/RECORD
